speech_recognition/__init__.py
speech_recognition/__main__.py
speech_recognition/flac-linux-x86
speech_recognition/flac-linux-x86_64
speech_recognition/flac-mac
speech_recognition/flac-win32.exe
speech_recognition/deepspeech-data/README
speech_recognition/pocketsphinx-data/en-US/LICENSE.txt
speech_recognition/pocketsphinx-data/en-US/language-model.lm.bin
speech_recognition/pocketsphinx-data/en-US/pronounciation-dictionary.dict
speech_recognition/pocketsphinx-data/en-US/acoustic-model/README
speech_recognition/pocketsphinx-data/en-US/acoustic-model/feat.params
speech_recognition/pocketsphinx-data/en-US/acoustic-model/mdef
speech_recognition/pocketsphinx-data/en-US/acoustic-model/means
speech_recognition/pocketsphinx-data/en-US/acoustic-model/noisedict
speech_recognition/pocketsphinx-data/en-US/acoustic-model/sendump
speech_recognition/pocketsphinx-data/en-US/acoustic-model/transition_matrices
speech_recognition/pocketsphinx-data/en-US/acoustic-model/variances
speech_recognition_fork-3.8.1.2021.6.14.dist-info/LICENSE-FLAC.txt
speech_recognition_fork-3.8.1.2021.6.14.dist-info/LICENSE.txt
speech_recognition_fork-3.8.1.2021.6.14.dist-info/METADATA
speech_recognition_fork-3.8.1.2021.6.14.dist-info/WHEEL
speech_recognition_fork-3.8.1.2021.6.14.dist-info/top_level.txt
speech_recognition_fork-3.8.1.2021.6.14.dist-info/RECORD
