Metadata-Version: 2.1
Name: speech-recognition-fork
Version: 3.8.1.2021.6.14
Summary: Library for performing speech recognition, with support for several engines and APIs, online and offline.
Home-page: https://github.com/avryhof/speech_recognition
Author: Anthony Zhang (Uberi)
Author-email: azhang9@gmail.com
License: BSD
Keywords: speech recognition voice sphinx google wit bing api houndify ibm snowboy
Platform: UNKNOWN
Classifier: Development Status :: 5 - Production/Stable
Classifier: Intended Audience :: Developers
Classifier: Natural Language :: English
Classifier: License :: OSI Approved :: BSD License
Classifier: Operating System :: Microsoft :: Windows
Classifier: Operating System :: POSIX :: Linux
Classifier: Operating System :: MacOS :: MacOS X
Classifier: Operating System :: Other OS
Classifier: Programming Language :: Python
Classifier: Programming Language :: Python :: 2
Classifier: Programming Language :: Python :: 2.7
Classifier: Programming Language :: Python :: 3
Classifier: Programming Language :: Python :: 3.3
Classifier: Programming Language :: Python :: 3.4
Classifier: Programming Language :: Python :: 3.5
Classifier: Programming Language :: Python :: 3.6
Classifier: Topic :: Software Development :: Libraries :: Python Modules
Classifier: Topic :: Multimedia :: Sound/Audio :: Speech
License-File: LICENSE.txt
License-File: LICENSE-FLAC.txt
